REGISTER.v
// Register module definition
/* 
- has input ports and output ports 
- flipflops, rise or fall depending on clock
- combinational circuits depend on current inputs, no connection to past inputs
- sequential circuits use memory, and outputs depend on current and prior inputs
- we write to output when read/write signal is high 
- we read value from memory when read/write signal is low
- flipflops are triggered at edges (sync) and latches are triggered with levels (over period of time; async)
*/

// verilog learning resources: 
/*
https://www.asic-world.com/verilog/verilog_one_day3.html
https://hwlabnitc.github.io/Verilog/registers.html
https://www.chipverify.com/tutorials/systemverilog
*/ 

module REGISTER (
    input iClk,              // Clock input
    input iRstN,             // Active low reset input
    input iWriteEn,          // Write enable input
    input iReadEnS1,         // Read enable input for source register 1
    input iReadEnS2,         // Read enable input for source register 2
    input [4:0] iRdAddr,     // 5 bit register address input
    input [4:0] iRs1Addr,    // 5 bit source register 1 address input
    input [4:0] iRs2Addr,    // 5 bit source register 2 address input
    input [31:0] iWriteData, // 32 bit data input to store in register
    output [31:0] oRs1Data,  // 32 bit source register 1 data output
    output [31:0] oRs2Data   // 32 bit source register 2 data output
);
    // vector with registers, 32 bits
    reg [31:0] registers [31:0];
    
    integer i;

    // writing is sequential
    // says to always execute when it's positive edge for the clock, or when we need to reset 
    always @(posedge iClk or negedge iRstN) begin
        // N stands for negative; iRstN is active when low
        // go ahead and reset all registers
        if (!iRstN) begin
            for(i=0; i<32; i=i+1) begin
                registers[i]<=32'b0; // sets to 0 in binary

            end 

        // read write logic
        end else begin
            // write
            // write only when iWriteEn is high and on postedge and additionally only when the address input is not x0
            if((iWriteEn) && (iRdAddr!=5'b0)) begin 
                registers[iRdAddr]<=iWriteData; // <= is non-blocking for sequential logic; = is combinational

            end


        end
    end

    // combinational logic
    // assign is for combinational logic, uses state buffers a lot

    // if read is enabled, check that it's not x0 before reading in the register data
    // repeat for both ports
    assign oRs1Data = (iReadEnS1!=1'b0) ? ((iRs1Addr==5'b0) ? (32'b0) : (registers[iRs1Addr])) : 32'b0;
    assign oRs2Data = (iReadEnS2!=1'b0) ? ((iRs2Addr==5'b0) ? (32'b0) : (registers[iRs2Addr])) : 32'b0;
            
    
endmodule

REGISTER_tb.v
`timescale 1ns/1ps

module REGISTER_tb;
    // Declare testbench signals
    reg tb_iClk;
    reg tb_iRstN;
    reg tb_iWriteEn;
    reg tb_iReadEnS1;
    reg tb_iReadEnS2;
    reg [4:0] tb_iRdAddr;
    reg [4:0] tb_iRs1Addr;
    reg [4:0] tb_iRs2Addr;
    reg [31:0] tb_iWriteData;
    wire [31:0] tb_oRs1Data;
    wire [31:0] tb_oRs2Data;

    // Instantiate the module under test
    REGISTER uut (
        .iClk(tb_iClk),
        .iRstN(tb_iRstN),
        .iWriteEn(tb_iWriteEn),
        .iReadEnS1(tb_iReadEnS1),
        .iReadEnS2(tb_iReadEnS2),
        .iRdAddr(tb_iRdAddr),
        .iRs1Addr(tb_iRs1Addr),
        .iRs2Addr(tb_iRs2Addr),
        .iWriteData(tb_iWriteData),
        .oRs1Data(tb_oRs1Data),
        .oRs2Data(tb_oRs2Data)
    );

    // Clock generation (50MHz = 20ns period)
    always #10 tb_iClk = ~tb_iClk;

    // Test sequence
    initial begin
        // Initialize signals
        tb_iClk = 0;
        tb_iRstN = 0;
        tb_iWriteEn = 0;
        tb_iReadEnS1 = 0;
        tb_iReadEnS2 = 0;
        tb_iRdAddr = 5'b0;
        tb_iRs1Addr = 5'b0;
        tb_iRs2Addr = 5'b0;
        tb_iWriteData = 32'b0;

        // Test 1: Reset test
        #20;
        tb_iRstN = 1;
        #20;
        
        // Test 2: Write to register x1
        tb_iWriteEn = 1;
        tb_iRdAddr = 5'd1;
        tb_iWriteData = 32'hDEADBEEF;
        #20;
        
        // Test 3: Write to register x5
        tb_iRdAddr = 5'd5;
        tb_iWriteData = 32'hCAFEBABE;
        #20;
        
        // Test 4: Try writing to x0 (should not work)
        tb_iRdAddr = 5'd0;
        tb_iWriteData = 32'h12345678;
        #20;
        
        tb_iWriteEn = 0;
        
        // Test 5: Read from x1 and x5
        tb_iReadEnS1 = 1;
        tb_iReadEnS2 = 1;
        tb_iRs1Addr = 5'd1;
        tb_iRs2Addr = 5'd5;
        #20;
        
        // Test 6: Read from x0 (should always be 0)
        tb_iRs1Addr = 5'd0;
        tb_iRs2Addr = 5'd0;
        #20;
        
        // Test 7: Simultaneous write and read
        tb_iWriteEn = 1;
        tb_iRdAddr = 5'd10;
        tb_iWriteData = 32'hABCD1234;
        tb_iRs1Addr = 5'd10;
        #20;
        
        // Test 8: Reset while holding data
        tb_iRstN = 0;
        #20;
        tb_iRstN = 1;
        tb_iReadEnS1 = 1;
        tb_iRs1Addr = 5'd1;
        #20;
        
        $display("All tests completed");
        $finish;
    end

    // Monitor changes
    initial begin
        $monitor("Time=%0t | Rst=%b | WE=%b | WAddr=%d | WData=%h | RS1=%d | RData1=%h | RS2=%d | RData2=%h",
                 $time, tb_iRstN, tb_iWriteEn, tb_iRdAddr, tb_iWriteData, 
                 tb_iRs1Addr, tb_oRs1Data, tb_iRs2Addr, tb_oRs2Data);
    end

    // Optional: Dump waveforms for viewing
    initial begin
        $dumpfile("register_tb.vcd");
        $dumpvars(0, REGISTER_tb);
    end

endmodule

register_tb.vcd
$date
	Mon Feb  9 15:02:42 2026
$end
$version
	Icarus Verilog
$end
$timescale
	1ps
$end
$scope module REGISTER_tb $end
$var wire 32 ! tb_oRs2Data [31:0] $end
$var wire 32 " tb_oRs1Data [31:0] $end
$var reg 1 # tb_iClk $end
$var reg 5 $ tb_iRdAddr [4:0] $end
$var reg 1 % tb_iReadEnS1 $end
$var reg 1 & tb_iReadEnS2 $end
$var reg 5 ' tb_iRs1Addr [4:0] $end
$var reg 5 ( tb_iRs2Addr [4:0] $end
$var reg 1 ) tb_iRstN $end
$var reg 32 * tb_iWriteData [31:0] $end
$var reg 1 + tb_iWriteEn $end
$scope module uut $end
$var wire 1 # iClk $end
$var wire 5 , iRdAddr [4:0] $end
$var wire 1 % iReadEnS1 $end
$var wire 1 & iReadEnS2 $end
$var wire 5 - iRs1Addr [4:0] $end
$var wire 5 . iRs2Addr [4:0] $end
$var wire 1 ) iRstN $end
$var wire 32 / iWriteData [31:0] $end
$var wire 1 + iWriteEn $end
$var wire 32 0 oRs2Data [31:0] $end
$var wire 32 1 oRs1Data [31:0] $end
$var integer 32 2 i [31:0] $end
$upscope $end
$upscope $end
$enddefinitions $end
$comment Show the parameter values. $end
$dumpall
$end
#0
$dumpvars
b100000 2
b0 1
b0 0
b0 /
b0 .
b0 -
b0 ,
0+
b0 *
0)
b0 (
b0 '
0&
0%
b0 $
0#
b0 "
b0 !
$end
#10000
b100000 2
1#
#20000
0#
1)
#30000
1#
#40000
0#
b11011110101011011011111011101111 *
b11011110101011011011111011101111 /
b1 $
b1 ,
1+
#50000
1#
#60000
0#
b11001010111111101011101010111110 *
b11001010111111101011101010111110 /
b101 $
b101 ,
#70000
1#
#80000
0#
b10010001101000101011001111000 *
b10010001101000101011001111000 /
b0 $
b0 ,
#90000
1#
#100000
b11001010111111101011101010111110 !
b11001010111111101011101010111110 0
b11011110101011011011111011101111 "
b11011110101011011011111011101111 1
0#
b101 (
b101 .
b1 '
b1 -
1&
1%
0+
#110000
1#
#120000
b0 !
b0 0
b0 "
b0 1
0#
b0 (
b0 .
b0 '
b0 -
#130000
1#
#140000
0#
b1010 '
b1010 -
b10101011110011010001001000110100 *
b10101011110011010001001000110100 /
b1010 $
b1010 ,
1+
#150000
b10101011110011010001001000110100 "
b10101011110011010001001000110100 1
1#
#160000
b0 "
b0 1
b100000 2
0#
0)
#170000
b100000 2
1#
#180000
0#
b1 '
b1 -
1)
